spyprof.py
spyprof-0.0.2.dist-info/licenses/LICENSE
spyprof-0.0.2.dist-info/METADATA
spyprof-0.0.2.dist-info/WHEEL
spyprof-0.0.2.dist-info/top_level.txt
spyprof-0.0.2.dist-info/RECORD
