Metadata-Version: 2.4
Name: spyprof
Version: 0.0.2
Summary: Sampling Python Profiler
Author-email: Yurii Zolotko <yurii.zolotko@pm.me>
License-Expression: BSD-3-Clause
Project-URL: Homepage, https://github.com/yuriiz/spyprof
Project-URL: Issues, https://github.com/yuriiz/spyprof/issues
Classifier: Programming Language :: Python :: 3
Classifier: Operating System :: OS Independent
Requires-Python: >=3.9
License-File: LICENSE
Requires-Dist: pygments
Dynamic: license-file
